shopify_client/__init__.py
shopify_client/add_product_to_collection.py
shopify_client/async_base_client.py
shopify_client/base_model.py
shopify_client/bulk_fetch_products.py
shopify_client/client.py
shopify_client/create_collection.py
shopify_client/create_product.py
shopify_client/create_product_variants_bulk.py
shopify_client/delete_collection.py
shopify_client/delete_product.py
shopify_client/enrich_product_data.py
shopify_client/enums.py
shopify_client/exceptions.py
shopify_client/get_bulk_operation.py
shopify_client/get_collection.py
shopify_client/get_collection_basic.py
shopify_client/get_collection_products.py
shopify_client/get_multiple_products_for_collection_sync.py
shopify_client/get_product.py
shopify_client/get_product_basic.py
shopify_client/get_product_collections.py
shopify_client/get_product_variants.py
shopify_client/get_shop.py
shopify_client/get_shop_details.py
shopify_client/get_shop_metafield.py
shopify_client/input_types.py
shopify_client/list_collections.py
shopify_client/list_products.py
shopify_client/remove_product_from_collection.py
shopify_client/set_metafield.py
shopify_client/update_collection.py
shopify_client/update_product.py
shopify_client/update_variants.py
shopify_catalog_client-0.3.0.dist-info/METADATA
shopify_catalog_client-0.3.0.dist-info/WHEEL
shopify_catalog_client-0.3.0.dist-info/licenses/LICENSE
shopify_catalog_client-0.3.0.dist-info/RECORD
