Metadata-Version: 2.4
Name: shopify-catalog-client
Version: 0.3.0
Summary: Python client for Shopify's product catalog GraphQL API
Project-URL: Homepage, https://github.com/marqo-ai/shopify-client
Author-email: Oliver Lade <oliver@marqo.ai>
License: MIT License
License-File: LICENSE
Keywords: api,client,graphql,product,shopify
Classifier: Programming Language :: Python :: 3
